{
  "annotations": {
    "list": [
      {
        "builtIn": 1,
        "datasource": {
          "type": "grafana",
          "uid": "-- Grafana --"
        },
        "enable": true,
        "hide": true,
        "iconColor": "rgba(0, 211, 255, 1)",
        "name": "Annotations & Alerts",
        "type": "dashboard"
      }
    ]
  },
  "editable": true,
  "fiscalYearStartMonth": 0,
  "graphTooltip": 0,
  "id": 1,
  "links": [],
  "panels": [
    {
      "collapsed": false,
      "gridPos": {
        "h": 1,
        "w": 24,
        "x": 0,
        "y": 0
      },
      "id": 20,
      "panels": [],
      "title": "Network Status Overview",
      "type": "row"
    },
    {
      "datasource": {
        "type": "postgres",
        "uid": "timescaledb"
      },
      "fieldConfig": {
        "defaults": {
          "color": {
            "mode": "thresholds"
          },
          "mappings": [],
          "thresholds": {
            "mode": "absolute",
            "steps": [
              {
                "color": "blue",
                "value": 0
              }
            ]
          },
          "unit": "short"
        },
        "overrides": []
      },
      "gridPos": {
        "h": 4,
        "w": 4,
        "x": 0,
        "y": 1
      },
      "id": 1,
      "options": {
        "colorMode": "value",
        "graphMode": "none",
        "justifyMode": "center",
        "orientation": "auto",
        "percentChangeColorMode": "standard",
        "reduceOptions": {
          "calcs": [
            "lastNotNull"
          ],
          "fields": "",
          "values": false
        },
        "showPercentChange": false,
        "textMode": "auto",
        "wideLayout": true
      },
      "pluginVersion": "12.3.0",
      "targets": [
        {
          "format": "table",
          "rawSql": "SELECT count(*) AS value FROM stridetastic_api_node;",
          "refId": "A"
        }
      ],
      "title": "Total Nodes",
      "type": "stat"
    },
    {
      "datasource": {
        "type": "postgres",
        "uid": "timescaledb"
      },
      "fieldConfig": {
        "defaults": {
          "color": {
            "mode": "thresholds"
          },
          "mappings": [],
          "thresholds": {
            "mode": "absolute",
            "steps": [
              {
                "color": "red",
                "value": 0
              },
              {
                "color": "yellow",
                "value": 5
              },
              {
                "color": "green",
                "value": 10
              }
            ]
          },
          "unit": "short"
        },
        "overrides": []
      },
      "gridPos": {
        "h": 4,
        "w": 4,
        "x": 4,
        "y": 1
      },
      "id": 2,
      "options": {
        "colorMode": "value",
        "graphMode": "none",
        "justifyMode": "center",
        "orientation": "auto",
        "percentChangeColorMode": "standard",
        "reduceOptions": {
          "calcs": [
            "lastNotNull"
          ],
          "fields": "",
          "values": false
        },
        "showPercentChange": false,
        "textMode": "auto",
        "wideLayout": true
      },
      "pluginVersion": "12.3.0",
      "targets": [
        {
          "format": "table",
          "rawSql": "SELECT count(*) AS value FROM stridetastic_api_node WHERE last_seen >= now() - interval '1 hour';",
          "refId": "A"
        }
      ],
      "title": "Online (1h)",
      "type": "stat"
    },
    {
      "datasource": {
        "type": "postgres",
        "uid": "timescaledb"
      },
      "fieldConfig": {
        "defaults": {
          "color": {
            "mode": "thresholds"
          },
          "mappings": [],
          "max": 100,
          "min": 0,
          "thresholds": {
            "mode": "absolute",
            "steps": [
              {
                "color": "red",
                "value": 0
              },
              {
                "color": "orange",
                "value": 50
              },
              {
                "color": "yellow",
                "value": 80
              },
              {
                "color": "green",
                "value": 90
              }
            ]
          },
          "unit": "percent"
        },
        "overrides": []
      },
      "gridPos": {
        "h": 4,
        "w": 4,
        "x": 8,
        "y": 1
      },
      "id": 3,
      "options": {
        "colorMode": "value",
        "graphMode": "none",
        "justifyMode": "center",
        "orientation": "auto",
        "percentChangeColorMode": "standard",
        "reduceOptions": {
          "calcs": [
            "lastNotNull"
          ],
          "fields": "",
          "values": false
        },
        "showPercentChange": false,
        "textMode": "auto",
        "wideLayout": true
      },
      "pluginVersion": "12.3.0",
      "targets": [
        {
          "format": "table",
          "rawSql": "SELECT round(100.0 * count(CASE WHEN last_seen >= now() - interval '1 hour' THEN 1 END) / NULLIF(count(*), 0), 2) AS value FROM stridetastic_api_node;",
          "refId": "A"
        }
      ],
      "title": "Online % (1h)",
      "type": "stat"
    },
    {
      "datasource": {
        "type": "postgres",
        "uid": "timescaledb"
      },
      "fieldConfig": {
        "defaults": {
          "color": {
            "mode": "thresholds"
          },
          "mappings": [],
          "thresholds": {
            "mode": "absolute",
            "steps": [
              {
                "color": "green",
                "value": 0
              },
              {
                "color": "yellow",
                "value": 1000
              },
              {
                "color": "orange",
                "value": 2000
              },
              {
                "color": "red",
                "value": 5000
              }
            ]
          },
          "unit": "ms"
        },
        "overrides": []
      },
      "gridPos": {
        "h": 4,
        "w": 4,
        "x": 12,
        "y": 1
      },
      "id": 4,
      "options": {
        "colorMode": "value",
        "graphMode": "none",
        "justifyMode": "center",
        "orientation": "auto",
        "percentChangeColorMode": "standard",
        "reduceOptions": {
          "calcs": [
            "lastNotNull"
          ],
          "fields": "",
          "values": false
        },
        "showPercentChange": false,
        "textMode": "auto",
        "wideLayout": true
      },
      "pluginVersion": "12.3.0",
      "targets": [
        {
          "format": "table",
          "rawSql": "SELECT COALESCE(round(avg(latency_ms)::numeric, 2), 0) AS value FROM stridetastic_api_nodelatencyhistory WHERE time >= now() - interval '5 minutes' AND latency_ms IS NOT NULL;",
          "refId": "A"
        }
      ],
      "title": "Avg Latency",
      "type": "stat"
    },
    {
      "datasource": {
        "type": "postgres",
        "uid": "timescaledb"
      },
      "fieldConfig": {
        "defaults": {
          "color": {
            "mode": "thresholds"
          },
          "mappings": [],
          "max": 100,
          "min": 0,
          "thresholds": {
            "mode": "absolute",
            "steps": [
              {
                "color": "red",
                "value": 0
              },
              {
                "color": "orange",
                "value": 70
              },
              {
                "color": "yellow",
                "value": 80
              },
              {
                "color": "green",
                "value": 90
              }
            ]
          },
          "unit": "percent"
        },
        "overrides": []
      },
      "gridPos": {
        "h": 4,
        "w": 4,
        "x": 16,
        "y": 1
      },
      "id": 5,
      "options": {
        "colorMode": "value",
        "graphMode": "none",
        "justifyMode": "center",
        "orientation": "auto",
        "percentChangeColorMode": "standard",
        "reduceOptions": {
          "calcs": [
            "lastNotNull"
          ],
          "fields": "",
          "values": false
        },
        "showPercentChange": false,
        "textMode": "auto",
        "wideLayout": true
      },
      "pluginVersion": "12.3.0",
      "targets": [
        {
          "format": "table",
          "rawSql": "SELECT COALESCE(round(100.0 * count(CASE WHEN latency_ms IS NOT NULL THEN 1 END) / NULLIF(count(*), 0), 2), 0) AS value FROM stridetastic_api_nodelatencyhistory WHERE time >= now() - interval '5 minutes';",
          "refId": "A"
        }
      ],
      "title": "Reachability %",
      "type": "stat"
    },
    {
      "datasource": {
        "type": "postgres",
        "uid": "timescaledb"
      },
      "fieldConfig": {
        "defaults": {
          "color": {
            "mode": "thresholds"
          },
          "mappings": [],
          "max": 100,
          "min": 0,
          "thresholds": {
            "mode": "absolute",
            "steps": [
              {
                "color": "red",
                "value": 0
              },
              {
                "color": "orange",
                "value": 20
              },
              {
                "color": "yellow",
                "value": 50
              },
              {
                "color": "green",
                "value": 70
              }
            ]
          },
          "unit": "percent"
        },
        "overrides": []
      },
      "gridPos": {
        "h": 4,
        "w": 4,
        "x": 20,
        "y": 1
      },
      "id": 6,
      "options": {
        "colorMode": "value",
        "graphMode": "none",
        "justifyMode": "center",
        "orientation": "auto",
        "percentChangeColorMode": "standard",
        "reduceOptions": {
          "calcs": [
            "lastNotNull"
          ],
          "fields": "",
          "values": false
        },
        "showPercentChange": false,
        "textMode": "auto",
        "wideLayout": true
      },
      "pluginVersion": "12.3.0",
      "targets": [
        {
          "format": "table",
          "rawSql": "SELECT COALESCE(round(avg(battery_level)::numeric, 2), 0) AS value FROM stridetastic_api_node WHERE battery_level IS NOT NULL AND last_seen >= now() - interval '24 hours';",
          "refId": "A"
        }
      ],
      "title": "Avg Battery %",
      "type": "stat"
    },
    {
      "collapsed": false,
      "gridPos": {
        "h": 1,
        "w": 24,
        "x": 0,
        "y": 5
      },
      "id": 21,
      "panels": [],
      "title": "Network Quality",
      "type": "row"
    },
    {
      "datasource": {
        "type": "postgres",
        "uid": "timescaledb"
      },
      "fieldConfig": {
        "defaults": {
          "color": {
            "mode": "thresholds"
          },
          "mappings": [],
          "thresholds": {
            "mode": "absolute",
            "steps": [
              {
                "color": "blue",
                "value": 0
              }
            ]
          },
          "unit": "short"
        },
        "overrides": []
      },
      "gridPos": {
        "h": 4,
        "w": 4,
        "x": 0,
        "y": 6
      },
      "id": 7,
      "options": {
        "colorMode": "value",
        "graphMode": "none",
        "justifyMode": "center",
        "orientation": "auto",
        "percentChangeColorMode": "standard",
        "reduceOptions": {
          "calcs": [
            "lastNotNull"
          ],
          "fields": "",
          "values": false
        },
        "showPercentChange": false,
        "textMode": "auto",
        "wideLayout": true
      },
      "pluginVersion": "12.3.0",
      "targets": [
        {
          "format": "table",
          "rawSql": "SELECT count(*) AS value FROM stridetastic_api_nodelink WHERE last_activity >= now() - interval '24 hours';",
          "refId": "A"
        }
      ],
      "title": "Active Links",
      "type": "stat"
    },
    {
      "datasource": {
        "type": "postgres",
        "uid": "timescaledb"
      },
      "fieldConfig": {
        "defaults": {
          "color": {
            "fixedColor": "green",
            "mode": "shades"
          },
          "custom": {
            "hideFrom": {
              "legend": false,
              "tooltip": false,
              "viz": false
            }
          },
          "mappings": []
        },
        "overrides": []
      },
      "gridPos": {
        "h": 7,
        "w": 4,
        "x": 4,
        "y": 6
      },
      "id": 11,
      "options": {
        "displayLabels": [
          "name",
          "value"
        ],
        "legend": {
          "displayMode": "list",
          "placement": "bottom",
          "showLegend": true
        },
        "pieType": "donut",
        "reduceOptions": {
          "calcs": [
            "lastNotNull"
          ],
          "fields": "/^value$/",
          "values": true
        },
        "sort": "desc",
        "tooltip": {
          "hideZeros": false,
          "mode": "single",
          "sort": "none"
        }
      },
      "pluginVersion": "12.3.0",
      "targets": [
        {
          "format": "table",
          "rawSql": "SELECT CASE WHEN is_bidirectional THEN 'Bidirectional' ELSE 'Unidirectional' END AS metric, count(*) AS value FROM stridetastic_api_nodelink WHERE last_activity >= now() - interval '24 hours' GROUP BY is_bidirectional;",
          "refId": "A"
        }
      ],
      "title": "Link Type Distribution",
      "type": "piechart"
    },
    {
      "datasource": {
        "type": "postgres",
        "uid": "timescaledb"
      },
      "fieldConfig": {
        "defaults": {
          "color": {
            "mode": "thresholds"
          },
          "mappings": [],
          "thresholds": {
            "mode": "absolute",
            "steps": [
              {
                "color": "red",
                "value": 0
              },
              {
                "color": "orange",
                "value": 2
              },
              {
                "color": "yellow",
                "value": 5
              },
              {
                "color": "green",
                "value": 10
              }
            ]
          },
          "unit": "dB"
        },
        "overrides": []
      },
      "gridPos": {
        "h": 4,
        "w": 4,
        "x": 8,
        "y": 6
      },
      "id": 9,
      "options": {
        "colorMode": "value",
        "graphMode": "none",
        "justifyMode": "center",
        "orientation": "auto",
        "percentChangeColorMode": "standard",
        "reduceOptions": {
          "calcs": [
            "lastNotNull"
          ],
          "fields": "",
          "values": false
        },
        "showPercentChange": false,
        "textMode": "auto",
        "wideLayout": true
      },
      "pluginVersion": "12.3.0",
      "targets": [
        {
          "format": "table",
          "rawSql": "SELECT COALESCE(round(avg(snr)::numeric, 2), 0) AS value FROM stridetastic_api_neighborinfoneighbor neigh WHERE payload_id IN (SELECT id FROM stridetastic_api_neighborinfopayload WHERE time >= now() - interval '5 minutes') AND snr IS NOT NULL;",
          "refId": "A"
        }
      ],
      "title": "Avg SNR",
      "type": "stat"
    },
    {
      "datasource": {
        "type": "postgres",
        "uid": "timescaledb"
      },
      "fieldConfig": {
        "defaults": {
          "color": {
            "mode": "thresholds"
          },
          "mappings": [],
          "thresholds": {
            "mode": "absolute",
            "steps": [
              {
                "color": "red",
                "value": 0
              },
              {
                "color": "orange",
                "value": -120
              },
              {
                "color": "yellow",
                "value": -100
              },
              {
                "color": "green",
                "value": -90
              }
            ]
          },
          "unit": "dBm"
        },
        "overrides": []
      },
      "gridPos": {
        "h": 4,
        "w": 4,
        "x": 12,
        "y": 6
      },
      "id": 8,
      "options": {
        "colorMode": "value",
        "graphMode": "none",
        "justifyMode": "center",
        "orientation": "auto",
        "percentChangeColorMode": "standard",
        "reduceOptions": {
          "calcs": [
            "lastNotNull"
          ],
          "fields": "",
          "values": false
        },
        "showPercentChange": false,
        "textMode": "auto",
        "wideLayout": true
      },
      "pluginVersion": "12.3.0",
      "targets": [
        {
          "format": "table",
          "rawSql": "SELECT COALESCE(round(avg(rx_rssi)::numeric, 2), 0) AS value FROM stridetastic_api_packet WHERE time >= now() - interval '1 hour' AND rx_rssi IS NOT NULL AND rx_rssi != 0;",
          "refId": "A"
        }
      ],
      "title": "Avg RSSI",
      "type": "stat"
    },
    {
      "datasource": {
        "type": "postgres",
        "uid": "timescaledb"
      },
      "fieldConfig": {
        "defaults": {
          "color": {
            "mode": "thresholds"
          },
          "mappings": [],
          "thresholds": {
            "mode": "absolute",
            "steps": [
              {
                "color": "blue",
                "value": 0
              }
            ]
          },
          "unit": "short"
        },
        "overrides": []
      },
      "gridPos": {
        "h": 4,
        "w": 4,
        "x": 16,
        "y": 6
      },
      "id": 18,
      "options": {
        "colorMode": "value",
        "graphMode": "none",
        "justifyMode": "center",
        "orientation": "auto",
        "percentChangeColorMode": "standard",
        "reduceOptions": {
          "calcs": [
            "lastNotNull"
          ],
          "fields": "",
          "values": false
        },
        "showPercentChange": false,
        "textMode": "auto",
        "wideLayout": true
      },
      "pluginVersion": "12.3.0",
      "targets": [
        {
          "format": "table",
          "rawSql": "SELECT count(*) AS value FROM stridetastic_api_packet WHERE time >= now() - interval '1 minute';",
          "refId": "A"
        }
      ],
      "title": "Packets/Last Min",
      "type": "stat"
    },
    {
      "datasource": {
        "type": "postgres",
        "uid": "timescaledb"
      },
      "fieldConfig": {
        "defaults": {
          "color": {
            "mode": "thresholds"
          },
          "mappings": [],
          "thresholds": {
            "mode": "absolute",
            "steps": [
              {
                "color": "blue",
                "value": 0
              }
            ]
          },
          "unit": "short"
        },
        "overrides": []
      },
      "gridPos": {
        "h": 4,
        "w": 4,
        "x": 20,
        "y": 6
      },
      "id": 10,
      "options": {
        "colorMode": "value",
        "graphMode": "none",
        "justifyMode": "center",
        "orientation": "auto",
        "percentChangeColorMode": "standard",
        "reduceOptions": {
          "calcs": [
            "lastNotNull"
          ],
          "fields": "",
          "values": false
        },
        "showPercentChange": false,
        "textMode": "auto",
        "wideLayout": true
      },
      "pluginVersion": "12.3.0",
      "targets": [
        {
          "format": "table",
          "rawSql": "SELECT COALESCE(round(count(*)::numeric / NULLIF(EXTRACT(EPOCH FROM ($__timeTo()::timestamp - $__timeFrom()::timestamp)) / 60, 0), 2), 0) AS value FROM stridetastic_api_packet WHERE time >= $__timeFrom()::timestamp AND time < $__timeTo()::timestamp;",
          "refId": "A"
        }
      ],
      "title": "Packets/Min",
      "type": "stat"
    },
    {
      "collapsed": false,
      "gridPos": {
        "h": 1,
        "w": 24,
        "x": 0,
        "y": 13
      },
      "id": 22,
      "panels": [],
      "title": "Time Series Trends (24 hour window)",
      "type": "row"
    },
    {
      "datasource": {
        "type": "postgres",
        "uid": "timescaledb"
      },
      "fieldConfig": {
        "defaults": {
          "color": {
            "mode": "palette-classic"
          },
          "custom": {
            "axisBorderShow": false,
            "axisCenteredZero": false,
            "axisColorMode": "text",
            "axisLabel": "",
            "axisPlacement": "auto",
            "barAlignment": 0,
            "barWidthFactor": 0.6,
            "drawStyle": "line",
            "fillOpacity": 0,
            "gradientMode": "none",
            "hideFrom": {
              "legend": false,
              "tooltip": false,
              "viz": false
            },
            "insertNulls": false,
            "lineInterpolation": "smooth",
            "lineWidth": 1,
            "pointSize": 5,
            "scaleDistribution": {
              "type": "linear"
            },
            "showPoints": "auto",
            "showValues": false,
            "spanNulls": false,
            "stacking": {
              "group": "A",
              "mode": "none"
            },
            "thresholdsStyle": {
              "mode": "off"
            }
          },
          "mappings": [],
          "thresholds": {
            "mode": "absolute",
            "steps": [
              {
                "color": "green",
                "value": 0
              },
              {
                "color": "red",
                "value": 80
              }
            ]
          }
        },
        "overrides": []
      },
      "gridPos": {
        "h": 8,
        "w": 12,
        "x": 0,
        "y": 14
      },
      "id": 12,
      "options": {
        "legend": {
          "calcs": [],
          "displayMode": "list",
          "placement": "bottom",
          "showLegend": true
        },
        "tooltip": {
          "hideZeros": false,
          "mode": "multi",
          "sort": "none"
        }
      },
      "pluginVersion": "12.3.0",
      "targets": [
        {
          "dataset": "postgres",
          "editorMode": "code",
          "format": "time_series",
          "rawQuery": true,
          "rawSql": "SELECT $__timeGroup(\"time\",$__interval) AS \"time\", active_nodes, reachable_nodes FROM stridetastic_api_networkoverviewsnapshot ORDER BY $__timeGroup(\"time\", $__interval) DESC ",
          "refId": "A",
          "sql": {
            "columns": [
              {
                "alias": "\"time\"",
                "name": "$__timeGroup",
                "parameters": [
                  {
                    "name": "\"time\"",
                    "type": "functionParameter"
                  },
                  {
                    "name": "$__interval",
                    "type": "functionParameter"
                  }
                ],
                "type": "function"
              },
              {
                "parameters": [
                  {
                    "name": "active_nodes",
                    "type": "functionParameter"
                  }
                ],
                "type": "function"
              },
              {
                "parameters": [
                  {
                    "name": "reachable_nodes",
                    "type": "functionParameter"
                  }
                ],
                "type": "function"
              }
            ],
            "groupBy": [],
            "limit": null,
            "orderBy": {
              "property": {
                "name": "$__timeGroup(\"time\", $__interval)",
                "type": "string"
              },
              "type": "property"
            },
            "orderByDirection": "DESC",
            "whereJsonTree": {
              "id": "bab98b9b-0123-4456-b89a-b19b525cebac",
              "type": "group"
            }
          },
          "table": "stridetastic_api_networkoverviewsnapshot"
        }
      ],
      "title": "Nodes Online Trend (1h window)",
      "type": "timeseries"
    },
    {
      "datasource": {
        "type": "postgres",
        "uid": "timescaledb"
      },
      "fieldConfig": {
        "defaults": {
          "color": {
            "mode": "palette-classic"
          },
          "custom": {
            "axisBorderShow": false,
            "axisCenteredZero": false,
            "axisColorMode": "text",
            "axisLabel": "",
            "axisPlacement": "auto",
            "barAlignment": 0,
            "barWidthFactor": 0.6,
            "drawStyle": "line",
            "fillOpacity": 0,
            "gradientMode": "none",
            "hideFrom": {
              "legend": false,
              "tooltip": false,
              "viz": false
            },
            "insertNulls": false,
            "lineInterpolation": "smooth",
            "lineWidth": 1,
            "pointSize": 5,
            "scaleDistribution": {
              "type": "linear"
            },
            "showPoints": "auto",
            "showValues": false,
            "spanNulls": true,
            "stacking": {
              "group": "A",
              "mode": "none"
            },
            "thresholdsStyle": {
              "mode": "off"
            }
          },
          "mappings": [],
          "thresholds": {
            "mode": "absolute",
            "steps": [
              {
                "color": "green",
                "value": 0
              },
              {
                "color": "red",
                "value": 80
              }
            ]
          }
        },
        "overrides": []
      },
      "gridPos": {
        "h": 8,
        "w": 12,
        "x": 12,
        "y": 14
      },
      "id": 13,
      "options": {
        "legend": {
          "calcs": [],
          "displayMode": "list",
          "placement": "bottom",
          "showLegend": true
        },
        "tooltip": {
          "hideZeros": false,
          "mode": "multi",
          "sort": "none"
        }
      },
      "pluginVersion": "12.3.0",
      "targets": [
        {
          "format": "time_series",
          "rawSql": "WITH minute_buckets AS (SELECT date_trunc('minute', ts)::timestamp AS bucket FROM generate_series($__timeFrom()::timestamp, $__timeTo()::timestamp, '1 minute'::interval) ts UNION ALL SELECT date_trunc('minute', now())::timestamp) SELECT DISTINCT mb.bucket::timestamp AS \"time\", avg(nlh.latency_ms)::numeric(8,2) AS value FROM minute_buckets mb LEFT JOIN stridetastic_api_nodelatencyhistory nlh ON nlh.time >= mb.bucket AND nlh.time < mb.bucket + interval '1 minute' AND nlh.latency_ms IS NOT NULL GROUP BY mb.bucket ORDER BY mb.bucket;",
          "refId": "A"
        }
      ],
      "title": "Latency Trend",
      "type": "timeseries"
    },
    {
      "datasource": {
        "type": "postgres",
        "uid": "timescaledb"
      },
      "fieldConfig": {
        "defaults": {
          "color": {
            "mode": "palette-classic"
          },
          "custom": {
            "axisBorderShow": false,
            "axisCenteredZero": false,
            "axisColorMode": "text",
            "axisLabel": "",
            "axisPlacement": "auto",
            "barAlignment": 0,
            "barWidthFactor": 0.6,
            "drawStyle": "line",
            "fillOpacity": 0,
            "gradientMode": "none",
            "hideFrom": {
              "legend": false,
              "tooltip": false,
              "viz": false
            },
            "insertNulls": false,
            "lineInterpolation": "smooth",
            "lineWidth": 1,
            "pointSize": 5,
            "scaleDistribution": {
              "type": "linear"
            },
            "showPoints": "auto",
            "showValues": false,
            "spanNulls": false,
            "stacking": {
              "group": "A",
              "mode": "none"
            },
            "thresholdsStyle": {
              "mode": "off"
            }
          },
          "mappings": [],
          "thresholds": {
            "mode": "absolute",
            "steps": [
              {
                "color": "green",
                "value": 0
              },
              {
                "color": "red",
                "value": 80
              }
            ]
          }
        },
        "overrides": []
      },
      "gridPos": {
        "h": 8,
        "w": 24,
        "x": 0,
        "y": 22
      },
      "id": 17,
      "options": {
        "legend": {
          "calcs": [],
          "displayMode": "list",
          "placement": "bottom",
          "showLegend": true
        },
        "tooltip": {
          "hideZeros": false,
          "mode": "multi",
          "sort": "none"
        }
      },
      "pluginVersion": "12.3.0",
      "targets": [
        {
          "format": "time_series",
          "rawSql": "WITH minute_buckets AS (SELECT date_trunc('minute', ts)::timestamp AS bucket FROM generate_series($__timeFrom()::timestamp, $__timeTo()::timestamp, '1 minute'::interval) ts UNION ALL SELECT date_trunc('minute', now())::timestamp) SELECT DISTINCT mb.bucket::timestamp AS \"time\", count(p.id) AS value FROM minute_buckets mb LEFT JOIN stridetastic_api_packet p ON p.time >= mb.bucket AND p.time < mb.bucket + interval '1 minute' GROUP BY mb.bucket ORDER BY mb.bucket;",
          "refId": "A"
        }
      ],
      "title": "Packets Sent Trend",
      "type": "timeseries"
    },
    {
      "datasource": {
        "type": "postgres",
        "uid": "timescaledb"
      },
      "fieldConfig": {
        "defaults": {
          "custom": {
            "align": "auto",
            "cellOptions": {
              "type": "auto"
            },
            "footer": {
              "reducers": []
            },
            "inspect": false,
            "width": "auto"
          },
          "mappings": [],
          "thresholds": {
            "mode": "absolute",
            "steps": [
              {
                "color": "green",
                "value": 0
              },
              {
                "color": "red",
                "value": 80
              }
            ]
          }
        },
        "overrides": [
          {
            "matcher": {
              "id": "byName",
              "options": "time"
            },
            "properties": [
              {
                "id": "custom.width",
                "value": 180
              }
            ]
          },
          {
            "matcher": {
              "id": "byName",
              "options": "from_node_id"
            },
            "properties": [
              {
                "id": "custom.width",
                "value": 120
              }
            ]
          },
          {
            "matcher": {
              "id": "byName",
              "options": "to_node_id"
            },
            "properties": [
              {
                "id": "custom.width",
                "value": 120
              }
            ]
          },
          {
            "matcher": {
              "id": "byName",
              "options": "from_short"
            },
            "properties": [
              {
                "id": "custom.width",
                "value": 80
              }
            ]
          },
          {
            "matcher": {
              "id": "byName",
              "options": "to_short"
            },
            "properties": [
              {
                "id": "custom.width",
                "value": 80
              }
            ]
          },
          {
            "matcher": {
              "id": "byName",
              "options": "port"
            },
            "properties": [
              {
                "id": "custom.width",
                "value": 150
              }
            ]
          }
        ]
      },
      "gridPos": {
        "h": 10,
        "w": 24,
        "x": 0,
        "y": 30
      },
      "id": 19,
      "options": {
        "cellHeight": "sm",
        "showHeader": true,
        "sortBy": [
          {
            "desc": false,
            "displayName": "time"
          }
        ]
      },
      "pluginVersion": "12.3.0",
      "targets": [
        {
          "format": "table",
          "rawSql": "SELECT p.time, fn.node_id AS from_node_id, fn.short_name AS from_short, fn.long_name AS from_long, tn.node_id AS to_node_id, tn.short_name AS to_short, tn.long_name AS to_long, pd.port, p.rx_rssi, p.rx_snr, p.hop_limit FROM stridetastic_api_packet p JOIN stridetastic_api_node fn ON p.from_node_id = fn.id JOIN stridetastic_api_node tn ON p.to_node_id = tn.id LEFT JOIN stridetastic_api_packetdata pd ON p.id = pd.packet_id WHERE p.time >= $__timeFrom()::timestamp AND p.time < $__timeTo()::timestamp ORDER BY p.time DESC LIMIT 500;",
          "refId": "A"
        }
      ],
      "title": "Packets Detail",
      "type": "table"
    },
    {
      "collapsed": false,
      "gridPos": {
        "h": 1,
        "w": 24,
        "x": 0,
        "y": 40
      },
      "id": 23,
      "panels": [],
      "title": "Detailed Metrics",
      "type": "row"
    },
    {
      "datasource": {
        "type": "postgres",
        "uid": "timescaledb"
      },
      "fieldConfig": {
        "defaults": {
          "color": {
            "mode": "palette-classic"
          },
          "custom": {
            "hideFrom": {
              "legend": false,
              "tooltip": false,
              "viz": false
            }
          },
          "mappings": [],
          "unit": "short"
        },
        "overrides": []
      },
      "gridPos": {
        "h": 14,
        "w": 8,
        "x": 0,
        "y": 41
      },
      "id": 14,
      "options": {
        "legend": {
          "displayMode": "list",
          "placement": "bottom",
          "showLegend": true
        },
        "pieType": "pie",
        "reduceOptions": {
          "calcs": [
            "lastNotNull"
          ],
          "fields": "",
          "values": true
        },
        "sort": "desc",
        "tooltip": {
          "hideZeros": false,
          "mode": "single",
          "sort": "none"
        }
      },
      "pluginVersion": "12.3.0",
      "targets": [
        {
          "format": "table",
          "rawSql": "SELECT COALESCE(pd.port, 'unknown') AS metric, count(*) AS value FROM stridetastic_api_packetdata pd JOIN stridetastic_api_packet p ON pd.packet_id = p.id WHERE p.time >= now() - interval '24 hours' GROUP BY pd.port ORDER BY value DESC;",
          "refId": "A"
        }
      ],
      "title": "Packet Distribution by Port",
      "type": "piechart"
    },
    {
      "datasource": {
        "type": "postgres",
        "uid": "timescaledb"
      },
      "fieldConfig": {
        "defaults": {
          "custom": {
            "align": "auto",
            "cellOptions": {
              "type": "auto"
            },
            "footer": {
              "reducers": []
            },
            "inspect": false
          },
          "mappings": [],
          "thresholds": {
            "mode": "absolute",
            "steps": [
              {
                "color": "green",
                "value": 0
              },
              {
                "color": "red",
                "value": 80
              }
            ]
          }
        },
        "overrides": []
      },
      "gridPos": {
        "h": 14,
        "w": 6,
        "x": 9,
        "y": 41
      },
      "id": 15,
      "options": {
        "cellHeight": "sm",
        "showHeader": true
      },
      "pluginVersion": "12.3.0",
      "targets": [
        {
          "format": "table",
          "rawSql": "SELECT CASE WHEN battery_level < 10 THEN 'Critical (<10%)' WHEN battery_level < 25 THEN 'Low (10-25%)' WHEN battery_level < 50 THEN 'Medium (25-50%)' WHEN battery_level < 75 THEN 'Good (50-75%)' ELSE 'Excellent (75%+)' END AS battery_bucket, count(*) AS node_count FROM stridetastic_api_node WHERE battery_level IS NOT NULL AND last_seen >= now() - interval '24 hours' GROUP BY battery_bucket ORDER BY node_count DESC;",
          "refId": "A"
        }
      ],
      "title": "Battery Distribution (Fleet)",
      "type": "table"
    },
    {
      "datasource": {
        "type": "postgres",
        "uid": "timescaledb"
      },
      "fieldConfig": {
        "defaults": {
          "color": {
            "mode": "palette-classic"
          },
          "custom": {
            "hideFrom": {
              "legend": false,
              "tooltip": false,
              "viz": false
            }
          },
          "mappings": [],
          "unit": "short"
        },
        "overrides": []
      },
      "gridPos": {
        "h": 14,
        "w": 8,
        "x": 16,
        "y": 41
      },
      "id": 16,
      "options": {
        "legend": {
          "displayMode": "list",
          "placement": "bottom",
          "showLegend": true
        },
        "pieType": "pie",
        "reduceOptions": {
          "calcs": [
            "lastNotNull"
          ],
          "fields": "",
          "values": true
        },
        "sort": "desc",
        "tooltip": {
          "hideZeros": false,
          "mode": "single",
          "sort": "none"
        }
      },
      "pluginVersion": "12.3.0",
      "targets": [
        {
          "format": "table",
          "rawSql": "WITH top_nodes AS (\n  SELECT n.node_id, n.short_name, COUNT(*) AS packets_sent\n  FROM stridetastic_api_packet p\n  JOIN stridetastic_api_node n ON p.from_node_id = n.id\n  WHERE p.time >= $__timeFrom()::timestamp AND p.time < $__timeTo()::timestamp\n  GROUP BY n.id, n.node_id, n.short_name\n  ORDER BY packets_sent DESC\n  LIMIT 10\n),\nall_packets AS (\n  SELECT COUNT(*) AS total_packets\n  FROM stridetastic_api_packet p\n  WHERE p.time >= $__timeFrom()::timestamp AND p.time < $__timeTo()::timestamp\n),\ntop_packets AS (\n  SELECT SUM(packets_sent) AS top_total\n  FROM top_nodes\n)\nSELECT tn.short_name AS name, tn.packets_sent AS packets\nFROM top_nodes tn\nUNION ALL\nSELECT 'Other nodes' AS name, (ap.total_packets - tp.top_total) AS packets\nFROM all_packets ap, top_packets tp\nORDER BY packets DESC;",
          "refId": "A"
        }
      ],
      "title": "Top Active Nodes (24h) vs All Others",
      "type": "piechart"
    },
    {
      "collapsed": false,
      "gridPos": {
        "h": 1,
        "w": 24,
        "x": 0,
        "y": 55
      },
      "id": 24,
      "panels": [],
      "title": "Health Status",
      "type": "row"
    },
    {
      "datasource": {
        "type": "postgres",
        "uid": "timescaledb"
      },
      "fieldConfig": {
        "defaults": {
          "custom": {
            "align": "auto",
            "cellOptions": {
              "type": "auto"
            },
            "footer": {
              "reducers": []
            },
            "inspect": false
          },
          "mappings": [],
          "thresholds": {
            "mode": "absolute",
            "steps": [
              {
                "color": "green",
                "value": 0
              },
              {
                "color": "red",
                "value": 80
              }
            ]
          }
        },
        "overrides": []
      },
      "gridPos": {
        "h": 6,
        "w": 24,
        "x": 0,
        "y": 56
      },
      "id": 25,
      "options": {
        "cellHeight": "sm",
        "showHeader": true
      },
      "pluginVersion": "12.2.1",
      "targets": [
        {
          "format": "table",
          "rawSql": "SELECT node_id, short_name, long_name, hw_model, battery_level, EXTRACT(HOUR FROM (now() - last_seen))::int AS hours_offline, last_seen FROM stridetastic_api_node WHERE last_seen < now() - interval '1 hour' AND first_seen >= now() - interval '7 days' ORDER BY last_seen ASC LIMIT 20;",
          "refId": "A"
        }
      ],
      "title": "Offline Nodes (>1h)",
      "type": "table"
    },
    {
      "datasource": {
        "type": "postgres",
        "uid": "timescaledb"
      },
      "fieldConfig": {
        "defaults": {
          "custom": {
            "align": "auto",
            "cellOptions": {
              "type": "auto"
            },
            "footer": {
              "reducers": []
            },
            "inspect": false
          },
          "mappings": [],
          "thresholds": {
            "mode": "absolute",
            "steps": [
              {
                "color": "green",
                "value": 0
              },
              {
                "color": "red",
                "value": 80
              }
            ]
          }
        },
        "overrides": []
      },
      "gridPos": {
        "h": 6,
        "w": 24,
        "x": 0,
        "y": 62
      },
      "id": 26,
      "options": {
        "cellHeight": "sm",
        "showHeader": true
      },
      "pluginVersion": "12.2.1",
      "targets": [
        {
          "format": "table",
          "rawSql": "SELECT node_id, short_name, long_name, hw_model, battery_level, latency_ms, last_seen FROM stridetastic_api_node WHERE battery_level IS NOT NULL AND battery_level < 50 AND last_seen >= now() - interval '24 hours' ORDER BY battery_level ASC LIMIT 20;",
          "refId": "A"
        }
      ],
      "title": "Low Battery Nodes (<50%)",
      "type": "table"
    }
  ],
  "preload": false,
  "refresh": "5m",
  "schemaVersion": 42,
  "tags": [
    "network",
    "health",
    "kpi",
    "overview"
  ],
  "templating": {
    "list": []
  },
  "time": {
    "from": "now-24h",
    "to": "now"
  },
  "timepicker": {},
  "timezone": "browser",
  "title": "A1 - Network Health KPI",
  "uid": "network-health-kpi",
  "version": 4
}